wagtail_heroicons/__init__.py
wagtail_heroicons/apps.py
wagtail_heroicons/py.typed
wagtail_heroicons/wagtail_hooks.py
wagtail_heroicons/templates/wagtail_heroicons/outline/academic-cap.svg
wagtail_heroicons/templates/wagtail_heroicons/outline/adjustments.svg
wagtail_heroicons/templates/wagtail_heroicons/outline/annotation.svg
wagtail_heroicons/templates/wagtail_heroicons/outline/archive.svg
wagtail_heroicons/templates/wagtail_heroicons/outline/arrow-circle-down.svg
wagtail_heroicons/templates/wagtail_heroicons/outline/arrow-circle-left.svg
wagtail_heroicons/templates/wagtail_heroicons/outline/arrow-circle-right.svg
wagtail_heroicons/templates/wagtail_heroicons/outline/arrow-circle-up.svg
wagtail_heroicons/templates/wagtail_heroicons/outline/arrow-down.svg
wagtail_heroicons/templates/wagtail_heroicons/outline/arrow-left.svg
wagtail_heroicons/templates/wagtail_heroicons/outline/arrow-narrow-down.svg
wagtail_heroicons/templates/wagtail_heroicons/outline/arrow-narrow-left.svg
wagtail_heroicons/templates/wagtail_heroicons/outline/arrow-narrow-right.svg
wagtail_heroicons/templates/wagtail_heroicons/outline/arrow-narrow-up.svg
wagtail_heroicons/templates/wagtail_heroicons/outline/arrow-right.svg
wagtail_heroicons/templates/wagtail_heroicons/outline/arrow-sm-down.svg
wagtail_heroicons/templates/wagtail_heroicons/outline/arrow-sm-left.svg
wagtail_heroicons/templates/wagtail_heroicons/outline/arrow-sm-right.svg
wagtail_heroicons/templates/wagtail_heroicons/outline/arrow-sm-up.svg
wagtail_heroicons/templates/wagtail_heroicons/outline/arrow-up.svg
wagtail_heroicons/templates/wagtail_heroicons/outline/arrows-expand.svg
wagtail_heroicons/templates/wagtail_heroicons/outline/at-symbol.svg
wagtail_heroicons/templates/wagtail_heroicons/outline/backspace.svg
wagtail_heroicons/templates/wagtail_heroicons/outline/badge-check.svg
wagtail_heroicons/templates/wagtail_heroicons/outline/ban.svg
wagtail_heroicons/templates/wagtail_heroicons/outline/beaker.svg
wagtail_heroicons-0.2.2.dist-info/METADATA
wagtail_heroicons-0.2.2.dist-info/WHEEL
wagtail_heroicons-0.2.2.dist-info/licenses/AUTHORS.md
wagtail_heroicons-0.2.2.dist-info/licenses/LICENSE
wagtail_heroicons-0.2.2.dist-info/RECORD
