Metadata-Version: 2.3
Name: wagtail-heroicons
Version: 0.2.2
Summary: Add Heroicons to the Wagtail admin.
Project-URL: Documentation, https://github.com/westerveltco/wagtail-heroicons
Project-URL: Issues, https://github.com/westerveltco/wagtail-heroicons/issues
Project-URL: Source, https://github.com/westerveltco/wagtail-heroicons
Author-email: Josh Thomas <josh@joshthomas.dev>
License: MIT License
License-File: AUTHORS.md
License-File: LICENSE
Classifier: Development Status :: 4 - Beta
Classifier: Framework :: Django
Classifier: Framework :: Django :: 3.2
Classifier: Framework :: Django :: 4.2
Classifier: Framework :: Django :: 5.0
Classifier: Framework :: Wagtail
Classifier: Framework :: Wagtail :: 5
Classifier: Framework :: Wagtail :: 6
Classifier: License :: OSI Approved :: MIT License
Classifier: Operating System :: OS Independent
Classifier: Programming Language :: Python
Classifier: Programming Language :: Python :: 3.8
Classifier: Programming Language :: Python :: 3.9
Classifier: Programming Language :: Python :: 3.10
Classifier: Programming Language :: Python :: 3.11
Classifier: Programming Language :: Python :: 3.12
Classifier: Programming Language :: Python :: Implementation :: CPython
Requires-Python: >=3.8
Requires-Dist: wagtail>=5.2
Provides-Extra: dev
Requires-Dist: beautifulsoup4; extra == 'dev'
Requires-Dist: bumpver; extra == 'dev'
Requires-Dist: coverage[toml]; extra == 'dev'
Requires-Dist: django-stubs; extra == 'dev'
Requires-Dist: environs; extra == 'dev'
Requires-Dist: hatch; extra == 'dev'
Requires-Dist: httpx; extra == 'dev'
Requires-Dist: mypy; extra == 'dev'
Requires-Dist: nodejs-bin; extra == 'dev'
Requires-Dist: nox[uv]; extra == 'dev'
Requires-Dist: pytest; extra == 'dev'
Requires-Dist: pytest-cov; extra == 'dev'
Requires-Dist: pytest-django; extra == 'dev'
Requires-Dist: pytest-randomly; extra == 'dev'
Requires-Dist: pytest-xdist; extra == 'dev'
Requires-Dist: ruff; extra == 'dev'
Requires-Dist: types-beautifulsoup4; extra == 'dev'
Provides-Extra: lint
Requires-Dist: pre-commit; extra == 'lint'
